{
  "doc_id": "c08d769d-0357-4f64-9dab-0d57d530bbfd",
  "title": "STANDARD FOR CHOCOLATE AND CHOCOLATE PRODUCTS CXS 87-1981",
  "sections": [
    {
      "section_id": 1,
      "order": 0,
      "section": "STANDARD FOR CHOCOLATE AND CHOCOLATE PRODUCTS CXS 87-1981",
      "summary": "Gives the title of the Codex Standard for Chocolate and Chocolate Products (CXS 87‑1981) and records its adoption in 1981, revision in 2003 and amendments in 2016 and 2022.",
      "categories": [
        "other"
      ],
      "subcategories": [
        "standard title",
        "adoption history"
      ],
      "page_range": {
        "start_page": 1,
        "end_page": 1
      }
    },
    {
      "section_id": 2,
      "order": 1,
      "section": "## 2022 Amendment",
      "summary": "Records a 2022 amendment replacing previous Section 5.3 on non‑retail container labelling with a requirement to follow the General Standard for the Labelling of Non‑Retail Containers of Foods (CXS 346‑2021).",
      "categories": [
        "other",
        "documentation",
        "labelling"
      ],
      "subcategories": [
        "amendment heading",
        "amendment note",
        "amendment table",
        "table separator",
        "non-retail labelling"
      ],
      "page_range": {
        "start_page": 2,
        "end_page": 2
      }
    },
    {
      "section_id": 3,
      "order": 2,
      "section": "1. SCOPE",
      "summary": "States the standard applies to chocolate and chocolate products listed in Section 2 intended for human consumption and specifies they shall be prepared from cocoa and cocoa materials with sugars and may contain sweeteners, milk products, flavourings and other food ingredients.",
      "categories": [
        "scope"
      ],
      "subcategories": [
        "scope heading",
        "applicability"
      ],
      "page_range": {
        "start_page": 3,
        "end_page": 3
      }
    },
    {
      "section_id": 4,
      "order": 3,
      "section": "2. DESCRIPTION AND ESSENTIAL COMPOSITION FACTORS",
      "summary": "Defines 'chocolate' as a homogeneous product from cocoa materials possibly combined with milk, sugars, sweeteners and permitted additives, limits other added edible foodstuffs to 40% of finished product and vegetable fats other than cocoa butter to 5% (without reducing minimum cocoa material requirements), and introduces detailed compositional specifications in Section 2.1.",
      "categories": [],
      "subcategories": [],
      "page_range": {
        "start_page": 3,
        "end_page": 7
      }
    },
    {
      "section_id": 5,
      "order": 4,
      "section": "2.1 Chocolate types (composition)",
      "summary": "Lists compositional requirements for various chocolate types (examples include: Chocolate—on a dry matter basis ≥35% total cocoa solids, ≥18% cocoa butter, ≥14% fat‑free cocoa solids; Sweet Chocolate ≥30% total cocoa solids with ≥18% cocoa butter and ≥12% fat‑free cocoa solids; Couverture ≥35% total with ≥31% cocoa butter; Milk Chocolate and other types have specified minimum cocoa and milk solids), and defines other products such as white chocolate, gianduja and chocolate para mesa with their minimum contents.",
      "categories": [],
      "subcategories": [],
      "page_range": {
        "start_page": 3,
        "end_page": 4
      }
    },
    {
      "section_id": 6,
      "order": 5,
      "section": "2.1.1 Chocolate",
      "summary": "Defines 'Chocolate' (also called bittersweet/semi‑sweet/dark) as containing on a dry matter basis not less than 35% total cocoa solids (of which at least 18% cocoa butter and 14% fat‑free cocoa solids) and defines 'Chocolate a la taza' as that product with a maximum of 8% m/m flour and/or starch from wheat, maize or rice.",
      "categories": [],
      "subcategories": [],
      "page_range": {
        "start_page": 3,
        "end_page": 3
      }
    },
    {
      "section_id": 7,
      "order": 6,
      "section": "2.1.2 Sweet Chocolate",
      "summary": "Sweet Chocolate must contain on a dry matter basis at least 30% total cocoa solids, of which at least 18% shall be cocoa butter and at least 12% fat-free cocoa solids; the related product \"chocolate familiar a la taza\" is the same type but may contain up to 18% (m/m) wheat, maize or rice flour/starch.",
      "categories": [],
      "subcategories": [],
      "page_range": {
        "start_page": 3,
        "end_page": 3
      }
    },
    {
      "section_id": 8,
      "order": 7,
      "section": "2.1.3 Couverture Chocolate",
      "summary": "Couverture Chocolate must contain on a dry matter basis not less than 35% total cocoa solids, including at least 31% cocoa butter and at least 2.5% fat-free cocoa solids.",
      "categories": [
        "classification",
        "composition"
      ],
      "subcategories": [
        "product class heading",
        "cocoa solids content"
      ],
      "page_range": {
        "start_page": 3,
        "end_page": 3
      }
    },
    {
      "section_id": 9,
      "order": 8,
      "section": "2.1.4 Milk Chocolate",
      "summary": "Milk Chocolate must contain on a dry matter basis not less than 25% cocoa solids (including at least 2.5% fat-free cocoa solids) and a specified minimum of milk solids between 12% and 14% (including milk fat 2.5–3.5%); the authority having jurisdiction applies the milk solids/milk fat minima, defines \"milk solids\" as milk ingredients in natural proportions (with milk fat optionally added or removed), and may set a minimum for cocoa butter plus milk fat where required.",
      "categories": [
        "classification",
        "composition",
        "definition"
      ],
      "subcategories": [
        "product class heading",
        "milk solids content",
        "milk solids definition",
        "optional minimum content"
      ],
      "page_range": {
        "start_page": 3,
        "end_page": 3
      }
    },
    {
      "section_id": 10,
      "order": 9,
      "section": "2.1.5 Family Milk Chocolate",
      "summary": "Family Milk Chocolate must contain on a dry matter basis at least 20% cocoa solids (including at least 2.5% fat-free cocoa solids) and at least 20% milk solids (including at least 5% milk fat); \"milk solids\" means milk ingredients in natural proportions except milk fat may be added or removed, and the competent authority may set a minimum for cocoa butter plus milk fat.",
      "categories": [
        "classification",
        "composition",
        "definition"
      ],
      "subcategories": [
        "product class heading",
        "milk solids content",
        "milk solids definition",
        "optional minimum content"
      ],
      "page_range": {
        "start_page": 3,
        "end_page": 3
      }
    },
    {
      "section_id": 11,
      "order": 10,
      "section": "2.1.6 Milk Chocolate Couverture",
      "summary": "Milk Chocolate Couverture must contain on a dry matter basis not less than 25% cocoa solids (including at least 2.5% non-fat cocoa solids), not less than 14% milk solids (including at least 3.5% milk fat) and a total fat of not less than 31%, with \"milk solids\" defined as milk ingredients in their natural proportions except milk fat may be added or removed.",
      "categories": [
        "classification",
        "composition",
        "definition"
      ],
      "subcategories": [
        "product class heading",
        "milk solids content",
        "milk solids definition"
      ],
      "page_range": {
        "start_page": 3,
        "end_page": 4
      }
    },
    {
      "section_id": 12,
      "order": 11,
      "section": "2.1.7 Other chocolate products",
      "summary": "This is a section heading for 'Other chocolate products' and contains no substantive provisions by itself.",
      "categories": [],
      "subcategories": [],
      "page_range": {
        "start_page": 4,
        "end_page": 4
      }
    },
    {
      "section_id": 13,
      "order": 12,
      "section": "2.1.7.1  White Chocolate",
      "summary": "White Chocolate must contain on a dry matter basis at least 20% cocoa butter and at least 14% milk solids (with minimum milk fat in the 2.5–3.5% range as applied by the authority); \"milk solids\" is defined as milk ingredients in natural proportions (milk fat may be added or removed), and the competent authority may set a minimum for cocoa butter plus milk fat.",
      "categories": [
        "classification",
        "composition",
        "definition"
      ],
      "subcategories": [
        "product class heading",
        "milk solids content",
        "milk solids definition",
        "optional minimum content"
      ],
      "page_range": {
        "start_page": 4,
        "end_page": 4
      }
    },
    {
      "section_id": 14,
      "order": 13,
      "section": "2.1.7.2  Gianduja Chocolate",
      "summary": "Gianduja Chocolate is made from chocolate with at least 32% total dry cocoa solids (including at least 8% dry non‑fat cocoa solids) combined with finely ground hazelnuts such that hazelnut content is between 20% and 40%; permitted additions include (a) milk/dry milk by evaporation provided finished product contains no more than 5% dry milk solids, and (b) whole or broken almonds, hazelnuts and other nuts provided that together with the ground hazelnuts they do not exceed 60% of total weight.",
      "categories": [
        "classification",
        "composition"
      ],
      "subcategories": [
        "product class heading",
        "hazelnut content",
        "permitted additions"
      ],
      "page_range": {
        "start_page": 4,
        "end_page": 4
      }
    },
    {
      "section_id": 15,
      "order": 14,
      "section": "2.1.7.3  Gianduja Milk Chocolate",
      "summary": "Gianduja Milk Chocolate is obtained from milk chocolate with a minimum dry milk solids content of 10% combined with finely ground hazelnuts to give 15–40% hazelnut content; \"milk solids\" are milk ingredients in natural proportions (milk fat may be added/removed), almonds/hazelnuts/other nuts may be added provided they and the ground hazelnuts do not exceed 60% of total weight, and the competent authority may set a minimum for cocoa butter plus milk fat.",
      "categories": [
        "classification",
        "composition",
        "definition"
      ],
      "subcategories": [
        "product class heading",
        "hazelnut content",
        "milk solids definition",
        "permitted additions",
        "optional minimum content"
      ],
      "page_range": {
        "start_page": 4,
        "end_page": 4
      }
    },
    {
      "section_id": 16,
      "order": 15,
      "section": "2.1.7.4  Chocolate para mesa",
      "summary": "This section defines 'Chocolate para mesa' as unrefined chocolate in which sugar grain size exceeds 70 microns.",
      "categories": [],
      "subcategories": [],
      "page_range": {
        "start_page": 4,
        "end_page": 4
      }
    },
    {
      "section_id": 17,
      "order": 16,
      "section": "2.1.7.4.1 Chocolate para mesa",
      "summary": "Chocolate para mesa must contain on a dry matter basis at least 20% total cocoa solids, including at least 11% cocoa butter and at least 9% fat-free cocoa solids.",
      "categories": [
        "classification",
        "composition"
      ],
      "subcategories": [
        "product class heading",
        "cocoa solids content"
      ],
      "page_range": {
        "start_page": 4,
        "end_page": 4
      }
    },
    {
      "section_id": 18,
      "order": 17,
      "section": "2.1.7.4.2 Semi-bitter chocolate para mesa",
      "summary": "Semi-bitter Chocolate para mesa must contain on a dry matter basis not less than 30% total cocoa solids, including at least 15% cocoa butter and at least 14% fat-free cocoa solids.",
      "categories": [
        "classification",
        "composition"
      ],
      "subcategories": [
        "product class heading",
        "cocoa solids content"
      ],
      "page_range": {
        "start_page": 4,
        "end_page": 4
      }
    },
    {
      "section_id": 19,
      "order": 18,
      "section": "2.1.7.4.3 Bitter chocolate para mesa",
      "summary": "Bitter Chocolate para mesa must contain on a dry matter basis at least 40% total cocoa solids, including at least 22% cocoa butter and at least 18% fat-free cocoa solids.",
      "categories": [
        "classification",
        "composition"
      ],
      "subcategories": [
        "product type heading",
        "cocoa content"
      ],
      "page_range": {
        "start_page": 4,
        "end_page": 4
      }
    },
    {
      "section_id": 20,
      "order": 19,
      "section": "2.2 Chocolate types (forms)",
      "summary": "Section 2.2 covers chocolate types/forms (vermicelli, flakes, filled chocolate, single‑bite chocolates/pralines) including production descriptions and compositional minima; it defines vermicelli/flakes by processing and shape and sets compositional minima for those and for filled chocolates (see subsections) and includes a summary table of the compositional requirements.",
      "categories": [],
      "subcategories": [],
      "page_range": {
        "start_page": 4,
        "end_page": 7
      }
    },
    {
      "section_id": 21,
      "order": 20,
      "section": "2.2.1 Chocolate Vermicelli and Chocolate Flakes",
      "summary": "Chocolate Vermicelli and Chocolate Flakes are cocoa products produced by mixing, extrusion and hardening to give crisp texture, presented as short cylindrical grains (vermicelli) or small flat pieces (flakes).",
      "categories": [],
      "subcategories": [],
      "page_range": {
        "start_page": 4,
        "end_page": 4
      }
    },
    {
      "section_id": 22,
      "order": 21,
      "section": "2.2.1.1  Chocolate Vermicelli / Chocolate Flakes",
      "summary": "Chocolate Vermicelli/Chocolate Flakes must contain on a dry matter basis at least 32% total cocoa solids, of which at least 12% shall be cocoa butter and 14% fat-free cocoa solids.",
      "categories": [
        "classification",
        "composition"
      ],
      "subcategories": [
        "product type heading",
        "cocoa content"
      ],
      "page_range": {
        "start_page": 4,
        "end_page": 4
      }
    },
    {
      "section_id": 23,
      "order": 22,
      "section": "2.2.1.2 Milk Chocolate Vermicelli/Milk Chocolate Flakes",
      "summary": "Milk Chocolate Vermicelli/Milk Chocolate Flakes must contain on a dry matter basis at least 20% cocoa solids (including at least 2.5% fat-free cocoa solids) and at least 12% milk solids (including at least 3% milk fat); \"milk solids\" are milk ingredients in natural proportions (milk fat may be added/removed) and the competent authority may set a minimum for cocoa butter plus milk fat.",
      "categories": [
        "classification",
        "composition"
      ],
      "subcategories": [
        "product type heading",
        "cocoa and milk content",
        "composition requirements"
      ],
      "page_range": {
        "start_page": 5,
        "end_page": 5
      }
    },
    {
      "section_id": 24,
      "order": 23,
      "section": "2.2.2 Filled Chocolate",
      "summary": "Filled Chocolate is a product coated with one or more of the chocolates defined in Section 2.1 (excluding chocolate a la taza, chocolate familiar a la taza and chocolate para mesa) whose center is compositionally distinct from the coating; the coating must constitute at least 25% of total product weight, the product excludes flour confectionery/pastry/biscuit/ice cream, and any center components covered by a separate Codex standard must comply with that standard.",
      "categories": [
        "classification",
        "composition"
      ],
      "subcategories": [
        "product type heading",
        "filled chocolate composition",
        "component compliance"
      ],
      "page_range": {
        "start_page": 5,
        "end_page": 5
      }
    },
    {
      "section_id": 25,
      "order": 24,
      "section": "2.2.3 A Chocolate or Praline",
      "summary": "A Chocolate or Praline is a single mouthful product in which the chocolate component is at least 25% of total weight and which consists of filled chocolate or one or more of the chocolates defined under Section 2.1 (excluding chocolate a la taza, chocolate familiar a la taza and chocolate para mesa).",
      "categories": [
        "classification",
        "composition"
      ],
      "subcategories": [
        "product type heading",
        "praline composition"
      ],
      "page_range": {
        "start_page": 5,
        "end_page": 5
      }
    },
    {
      "section_id": 26,
      "order": 25,
      "section": "TABLE 1. SUMMARY TABLE OF COMPOSITIONAL REQUIREMENTS OF SECTION 2 1",
      "summary": "Table 1 is a summary table of compositional requirements (percentages on a dry matter basis after deducting authorized additional edible foodstuffs) for the chocolate types in Section 2.1, listing minima for cocoa butter, fat‑free cocoa solids, total cocoa solids, milk fat, total milk solids, starch/flour and hazelnuts where applicable.",
      "categories": [],
      "subcategories": [],
      "page_range": {
        "start_page": 6,
        "end_page": 6
      }
    },
    {
      "section_id": 27,
      "order": 26,
      "section": "2. Chocolate Types",
      "summary": "Table header listing composition attributes used for chocolate types: cocoa butter, fat‑free cocoa solids, total cocoa solids, milk fat, total milk solids, starch/flour, and hazelnuts (non‑substantive on its own).",
      "categories": [],
      "subcategories": [],
      "page_range": {
        "start_page": 6,
        "end_page": 6
      }
    },
    {
      "section_id": 28,
      "order": 27,
      "section": "2.1 CHOCOLATE TYPES (COMPOSITION)",
      "summary": "Section heading for 'CHOCOLATE TYPES (COMPOSITION)' with no substantive compositional requirements beyond the heading itself.",
      "categories": [],
      "subcategories": [],
      "page_range": {
        "start_page": 6,
        "end_page": 6
      }
    },
    {
      "section_id": 29,
      "order": 28,
      "section": "2.1.1 Chocolate",
      "summary": "Defines 'Chocolate' composition requiring at least 18% cocoa butter, at least 14% fat‑free cocoa solids and at least 35% total cocoa solids.",
      "categories": [],
      "subcategories": [],
      "page_range": {
        "start_page": 6,
        "end_page": 6
      }
    },
    {
      "section_id": 30,
      "order": 29,
      "section": "2.1.1.1 Chocolate a la taza",
      "summary": "'Chocolate a la taza' composition: minimum 18% cocoa butter, minimum 14% fat‑free cocoa solids, minimum 35% total cocoa solids, and starch/flour less than 8%.",
      "categories": [
        "composition"
      ],
      "subcategories": [
        "product composition table"
      ],
      "page_range": {
        "start_page": 6,
        "end_page": 6
      }
    },
    {
      "section_id": 31,
      "order": 30,
      "section": "2.1.2 Sweet Chocolat",
      "summary": "'Sweet Chocolat' composition requiring at least 18% cocoa butter, at least 12% fat‑free cocoa solids and at least 30% total cocoa solids.",
      "categories": [],
      "subcategories": [],
      "page_range": {
        "start_page": 6,
        "end_page": 6
      }
    },
    {
      "section_id": 32,
      "order": 31,
      "section": "2.1.2.1 Chocolate familiar a la taza",
      "summary": "'Chocolate familiar a la taza' composition: minimum 18% cocoa butter, minimum 12% fat‑free cocoa solids, minimum 30% total cocoa solids, and starch/flour less than 18%.",
      "categories": [
        "composition"
      ],
      "subcategories": [
        "product composition table"
      ],
      "page_range": {
        "start_page": 6,
        "end_page": 6
      }
    },
    {
      "section_id": 33,
      "order": 32,
      "section": "2.1.3 Couverture Chocolate",
      "summary": "'Couverture Chocolate' composition requiring at least 31% cocoa butter, at least 2.5% fat‑free cocoa solids and at least 35% total cocoa solids.",
      "categories": [
        "composition"
      ],
      "subcategories": [
        "product composition table"
      ],
      "page_range": {
        "start_page": 6,
        "end_page": 6
      }
    },
    {
      "section_id": 34,
      "order": 33,
      "section": "2.1.4 Milk Chocolate",
      "summary": "'Milk Chocolate' composition requiring at least 2.5% fat‑free cocoa solids and at least 25% total cocoa solids, with milk fat in the range 2.5–3.5% and total milk solids 12–14%.",
      "categories": [
        "composition"
      ],
      "subcategories": [
        "product composition table"
      ],
      "page_range": {
        "start_page": 6,
        "end_page": 6
      }
    },
    {
      "section_id": 35,
      "order": 34,
      "section": "2.1.5 Family Milk Chocolate",
      "summary": "'Family Milk Chocolate' composition requiring at least 2.5% fat‑free cocoa solids, at least 20% total cocoa solids, milk fat at least 5% and total milk solids at least 20%.",
      "categories": [
        "composition"
      ],
      "subcategories": [
        "product composition table"
      ],
      "page_range": {
        "start_page": 6,
        "end_page": 6
      }
    },
    {
      "section_id": 36,
      "order": 35,
      "section": "2.1.6 Milk Chocolate couverture",
      "summary": "'Milk Chocolate couverture' composition requiring at least 2.5% fat‑free cocoa solids, at least 25% total cocoa solids, milk fat at least 3.5% and total milk solids at least 14%.",
      "categories": [
        "composition"
      ],
      "subcategories": [
        "product composition table"
      ],
      "page_range": {
        "start_page": 6,
        "end_page": 6
      }
    },
    {
      "section_id": 37,
      "order": 36,
      "section": "2.1.7 Other chocolate products",
      "summary": "Section heading 'Other chocolate products' with no substantive compositional details in the text provided.",
      "categories": [],
      "subcategories": [],
      "page_range": {
        "start_page": 6,
        "end_page": 6
      }
    },
    {
      "section_id": 38,
      "order": 37,
      "section": "2.1.7.1. White Chocolate",
      "summary": "'White Chocolate' composition requiring at least 20% cocoa butter, milk fat in the range 2.5–3.5% and total milk solids at least 14%.",
      "categories": [
        "composition"
      ],
      "subcategories": [
        "product composition table"
      ],
      "page_range": {
        "start_page": 6,
        "end_page": 6
      }
    },
    {
      "section_id": 39,
      "order": 38,
      "section": "2.1.7.2 Gianduja Chocolate",
      "summary": "'Gianduja Chocolate' composition requiring at least 8% fat‑free cocoa solids, at least 32% total cocoa solids and hazelnut content between 20% and 40%.",
      "categories": [
        "composition"
      ],
      "subcategories": [
        "product composition table"
      ],
      "page_range": {
        "start_page": 6,
        "end_page": 6
      }
    },
    {
      "section_id": 40,
      "order": 39,
      "section": "2.1.7.3 Gianduja Milk Chocolate",
      "summary": "'Gianduja Milk Chocolate' composition requiring at least 2.5% fat‑free cocoa solids, at least 25% total cocoa solids, milk fat 2.5–3.5%, total milk solids at least 10%, and hazelnut content between 15% and 40%.",
      "categories": [
        "composition"
      ],
      "subcategories": [
        "product composition table"
      ],
      "page_range": {
        "start_page": 6,
        "end_page": 6
      }
    },
    {
      "section_id": 41,
      "order": 40,
      "section": "2.1.7.4 Chocolate para mesa",
      "summary": "Section heading 'Chocolate para mesa' with no substantive compositional details in the text provided.",
      "categories": [],
      "subcategories": [],
      "page_range": {
        "start_page": 6,
        "end_page": 6
      }
    },
    {
      "section_id": 42,
      "order": 41,
      "section": "2.2 CHOCOLATE TYPES (forms)",
      "summary": "Section heading 'CHOCOLATE TYPES (forms)' only, without substantive requirements in the provided text.",
      "categories": [],
      "subcategories": [],
      "page_range": {
        "start_page": 7,
        "end_page": 7
      }
    },
    {
      "section_id": 43,
      "order": 42,
      "section": "2.2.1 Chocolate Vermicelli / Chocolate Flakes",
      "summary": "'Chocolate Vermicelli / Chocolate Flakes' composition requiring minimums of approximately 12% cocoa butter, 14% fat‑free cocoa solids and 32% total cocoa solids (table row of compositional minima).",
      "categories": [],
      "subcategories": [],
      "page_range": {
        "start_page": 7,
        "end_page": 7
      }
    },
    {
      "section_id": 44,
      "order": 43,
      "section": "2.2.2 Filled Chocolate (see section 2.2.2)",
      "summary": "Classification heading 'Filled Chocolate (see section 2.2.2)' only, not substantive on its own.",
      "categories": [
        "classification"
      ],
      "subcategories": [
        "product type heading"
      ],
      "page_range": {
        "start_page": 7,
        "end_page": 7
      }
    },
    {
      "section_id": 45,
      "order": 44,
      "section": "2.2.3 A Chocolate or Praline (see section 2.2.3)",
      "summary": "Classification heading 'A Chocolate or Praline (see section 2.2.3)' only, not substantive on its own.",
      "categories": [
        "classification"
      ],
      "subcategories": [
        "product type heading"
      ],
      "page_range": {
        "start_page": 7,
        "end_page": 7
      }
    },
    {
      "section_id": 46,
      "order": 45,
      "section": "3. FOOD ADDITIVES",
      "summary": "Permits certain additives for chocolate products: acidity regulators, antioxidants, bulking agents, surface‑decoration colours, emulsifiers, glazing agents and sweeteners per Tables 1–2 of the GSFA (CXS 192‑1995) with only specified Table 3 additives allowed; flavourings must follow CXG 66‑2008 and not imitate chocolate or milk (vanillin and ethyl vanillin are exceptions up to 1000 mg/kg combined), and processing aids must follow CXG 75‑2010 with hexane limited to 1 mg/kg on a fat‑content basis.",
      "categories": [],
      "subcategories": [],
      "page_range": {
        "start_page": 7,
        "end_page": 7
      }
    },
    {
      "section_id": 47,
      "order": 46,
      "section": "3.1 Acidity regulators, antioxidants, bulking agents, colours (for surface decoration purposes only), emulsifiers, glazing agents and sweeteners used in accordance with Tables 1 and 2 of the General Standard for Food Additives (CXS 192-1995) in food category 05.1.4 (Chocolate and chocolate products) and its parent food categories are acceptable for use in foods conforming to this standard. Only certain Table 3 food additives (as indicated in Table 3) are acceptable for use in foods conforming to this standard.",
      "summary": "Permits use of acidity regulators, antioxidants, bulking agents, surface-decoration colours, emulsifiers, glazing agents and sweeteners in chocolate (food category 05.1.4 and parents) only as listed in Tables 1 and 2 of the General Standard for Food Additives (CXS 192-1995), and allows only certain Table 3 additives where indicated in Table 3.",
      "categories": [
        "additives"
      ],
      "subcategories": [
        "permitted additives"
      ],
      "page_range": {
        "start_page": 7,
        "end_page": 7
      }
    },
    {
      "section_id": 48,
      "order": 47,
      "section": "3.2 The flavourings used in products covered by this standard should comply with the Guidelines for the Use of Flavourings (CXG 66-2008). Only those flavourings that do not imitate chocolate or milk flavours are permitted at GMP for products described under 2.1 and 2.2, except for vanillin and ethyl vanillin at a maximum level of 1000 mg/kg, singly or in combination.",
      "summary": "Requires flavourings to comply with the Guidelines for the Use of Flavourings (CXG 66-2008) and permits only flavourings that do not imitate chocolate or milk at GMP for products under Sections 2.1 and 2.2, except vanillin and ethyl vanillin which may be used up to 1000 mg/kg singly or combined.",
      "categories": [
        "additives"
      ],
      "subcategories": [
        "flavouring restrictions"
      ],
      "page_range": {
        "start_page": 7,
        "end_page": 7
      }
    },
    {
      "section_id": 49,
      "order": 48,
      "section": "3.3",
      "summary": "Specifies processing aids consistent with CXG 75-2010 and sets a maximum hexane residue limit of 1 mg/kg (calculated on a fat content basis) for hexane (62–82°C) used as a processing aid.",
      "categories": [
        "additives"
      ],
      "subcategories": [
        "processing aids heading",
        "processing aids table",
        "processing aid limit",
        "processing aid guidance"
      ],
      "page_range": {
        "start_page": 7,
        "end_page": 7
      }
    },
    {
      "section_id": 50,
      "order": 49,
      "section": "4. HYGIENE",
      "summary": "Recommends preparing and handling products in accordance with Codex hygienic texts (General Principles of Food Hygiene CXC 1-1969, Code for Low Moisture Foods CXC 75-2015 and other relevant Codes of Practice) and requires compliance with any microbiological criteria established per CXG 21-1997.",
      "categories": [
        "hygiene"
      ],
      "subcategories": [
        "hygiene heading",
        "hygienic preparation",
        "microbiological criteria"
      ],
      "page_range": {
        "start_page": 7,
        "end_page": 7
      }
    },
    {
      "section_id": 51,
      "order": 50,
      "section": "5. LABELLING",
      "summary": "Adds specific labelling requirements beyond the General Standard for the Labelling of Pre-packaged Foods (CXS 1/119‑85), including product naming rules (see Section 5.1 subsections), declarations when sugars are replaced by sweeteners or vegetable fats are used, minimum cocoa content declarations where required, and non-retail container labelling per CXS 346-2021.",
      "categories": [],
      "subcategories": [],
      "page_range": {
        "start_page": 7,
        "end_page": 8
      }
    },
    {
      "section_id": 52,
      "order": 51,
      "section": "5.1.2 Filled Chocolate",
      "summary": "Requires products defined under Section 2.2.2 to be designated 'Filled Chocolate', 'X Filled Chocolate', 'Chocolate with X Filling' or 'Chocolate with X Centre' (X descriptive of filling), allows specifying the external coating type per Section 5.1.1 designations, and mandates a clear statement informing consumers of the nature of the centre.",
      "categories": [
        "labelling"
      ],
      "subcategories": [
        "labelling subheading",
        "product designation",
        "coating declaration",
        "centre declaration"
      ],
      "page_range": {
        "start_page": 8,
        "end_page": 8
      }
    },
    {
      "section_id": 53,
      "order": 52,
      "section": "5.1.3 A Chocolate or Praline",
      "summary": "States that single mouthful products under Section 2.2.3 shall be designated 'A Chocolate' or 'Praline'.",
      "categories": [
        "labelling"
      ],
      "subcategories": [
        "labelling subheading",
        "product designation"
      ],
      "page_range": {
        "start_page": 8,
        "end_page": 8
      }
    },
    {
      "section_id": 54,
      "order": 53,
      "section": "5.1.4 Assorted Chocolates",
      "summary": "Allows assortments of products (excluding certain table chocolates) to be labelled with an assortment designation (e.g. 'Assorted Chocolates') provided there is either a single ingredients list for the assortment or separate ingredient lists by product.",
      "categories": [
        "labelling"
      ],
      "subcategories": [
        "labelling subheading",
        "assortment ingredients"
      ],
      "page_range": {
        "start_page": 8,
        "end_page": 8
      }
    },
    {
      "section_id": 55,
      "order": 54,
      "section": "5.1.5 Other Information Required",
      "summary": "Requires any characterizing flavour other than chocolate, and particularly aromatic ingredients that characterize the product, to be included in the product name or designation (e.g. 'Mocca Chocolate').",
      "categories": [
        "labelling"
      ],
      "subcategories": [
        "labelling subheading",
        "characterizing flavour",
        "product name declaration"
      ],
      "page_range": {
        "start_page": 8,
        "end_page": 8
      }
    },
    {
      "section_id": 56,
      "order": 55,
      "section": "5.1.6 Use of the Term Chocolate",
      "summary": "Permits use of the term 'chocolate' for products not defined by this standard whose chocolate taste derives solely from non‑fat cocoa solids, subject to national provisions or customary practice and provided they cannot be confused with products defined in this standard.",
      "categories": [
        "labelling"
      ],
      "subcategories": [
        "labelling subheading",
        "use of chocolate"
      ],
      "page_range": {
        "start_page": 8,
        "end_page": 8
      }
    },
    {
      "section_id": 57,
      "order": 56,
      "section": "5.2 Declaration of minimum cocoa content",
      "summary": "When required by the competent authority, products in Section 2.1 (except white chocolate) must carry a declaration of cocoa solids expressed as a percentage calculated on the chocolate part after deducting other permitted edible foodstuffs.",
      "categories": [
        "labelling"
      ],
      "subcategories": [
        "labelling subheading",
        "cocoa solids declaration"
      ],
      "page_range": {
        "start_page": 8,
        "end_page": 8
      }
    },
    {
      "section_id": 58,
      "order": 57,
      "section": "5.3 Labelling of non-retail containers",
      "summary": "States that labelling of non-retail containers should follow the General Standard for the Labelling of Non-Retail Containers of Foods (CXS 346-2021).",
      "categories": [
        "labelling"
      ],
      "subcategories": [
        "labelling subheading",
        "non-retail containers"
      ],
      "page_range": {
        "start_page": 8,
        "end_page": 8
      }
    },
    {
      "section_id": 59,
      "order": 58,
      "section": "6. METHODS OF ANALYSIS AND SAMPLING",
      "summary": "Prescribes methods of analysis and sampling for chocolate products, listing approved AOAC/IOCCC methods for determinations (centre/coating, cocoa butter, fat‑free cocoa and milk solids, milk fat, moisture, total fat) and providing specific methods and interpretation guidance for detection and quantification of non‑cocoa butter vegetable fats (AOCS, GC‑FID references) with a requirement to provide documentation on commercial blends to competent authorities.",
      "categories": [],
      "subcategories": [],
      "page_range": {
        "start_page": 8,
        "end_page": 9
      }
    },
    {
      "section_id": 60,
      "order": 59,
      "section": "6.1 Determination of centre and coating of filled chocolate",
      "summary": "Specifies that determination of the centre and coating of filled chocolate shall use any methods approved for the specific chocolate coating type and for the type of centre concerned.",
      "categories": [
        "analysis sampling"
      ],
      "subcategories": [
        "analysis method heading",
        "analysis method"
      ],
      "page_range": {
        "start_page": 8,
        "end_page": 8
      }
    },
    {
      "section_id": 61,
      "order": 60,
      "section": "6.2 Determination of cocoa butter",
      "summary": "States that cocoa butter content shall be determined according to AOAC 963.15 or IOCCC 14-1972.",
      "categories": [
        "analysis sampling"
      ],
      "subcategories": [
        "analysis method heading",
        "analysis method"
      ],
      "page_range": {
        "start_page": 8,
        "end_page": 8
      }
    },
    {
      "section_id": 62,
      "order": 61,
      "section": "6.3 Determination of fat-free cocoa solid",
      "summary": "Specifies determination of fat‑free cocoa solids according to AOAC 931.05.",
      "categories": [
        "analysis sampling"
      ],
      "subcategories": [
        "analysis method heading",
        "analysis method"
      ],
      "page_range": {
        "start_page": 8,
        "end_page": 8
      }
    },
    {
      "section_id": 63,
      "order": 62,
      "section": "6.4 Determination of fat-free milk solids",
      "summary": "Specifies determination of fat‑free milk solids according to IOCCC 17-1973 or AOAC 939.02.",
      "categories": [
        "analysis sampling"
      ],
      "subcategories": [
        "analysis method heading",
        "analysis method"
      ],
      "page_range": {
        "start_page": 8,
        "end_page": 8
      }
    },
    {
      "section_id": 64,
      "order": 63,
      "section": "6.5 Determination of milk fat",
      "summary": "Specifies determination of milk fat according to IOCCC 5-1962 or AOAC methods 945.34, 925.41B, or 920.80.",
      "categories": [
        "analysis sampling"
      ],
      "subcategories": [
        "analysis method heading",
        "analysis method"
      ],
      "page_range": {
        "start_page": 8,
        "end_page": 8
      }
    },
    {
      "section_id": 65,
      "order": 64,
      "section": "6.6 Determination of moisture",
      "summary": "Specifies determination of moisture by IOCCC 26-1988 or AOAC 977.10 (Karl Fischer method), or by AOAC 931.04 or IOCCC 1-1952 (gravimetric methods).",
      "categories": [
        "analysis sampling"
      ],
      "subcategories": [
        "analysis method heading",
        "analysis method"
      ],
      "page_range": {
        "start_page": 8,
        "end_page": 8
      }
    },
    {
      "section_id": 66,
      "order": 65,
      "section": "6.7 Determination of total fat",
      "summary": "Specifies determination of total fat according to AOAC 963.15.",
      "categories": [
        "analysis sampling"
      ],
      "subcategories": [
        "analysis method heading",
        "analysis method"
      ],
      "page_range": {
        "start_page": 9,
        "end_page": 9
      }
    },
    {
      "section_id": 67,
      "order": 66,
      "section": "6.8 Determination of non-cocoa butter vegetable fat in chocolate and chocolate products",
      "summary": "Sets out the best-available methods (subject to further improvement) and documentation requirements for detecting and quantifying non‑cocoa‑butter vegetable fats in chocolate: detection by sterol breakdown (AOCS Ce 10/02), quantitative triacylglycerol profiling (GC‑FID for C50, C52, C54) with milk‑fat correction for milk chocolate, interpretation/calculation methods depending on whether the vegetable‑fat type is known (J. Amer. Oil Chem. Soc. 1980 or 1982), and notes that the quantitative method targets cocoa‑butter equivalents (SOS triglycerides) while other vegetable fats are assessed by conventional fatty acid/triacylglycerol analyses; competent authorities may request documentation on commercial fat blends.",
      "categories": [],
      "subcategories": [],
      "page_range": {
        "start_page": 9,
        "end_page": 9
      }
    },
    {
      "section_id": 68,
      "order": 67,
      "section": "6.8.1 Detection of Non-Cocoa Butter Vegetable Fats in Chocolate",
      "summary": "Specifies detection of sterol breakdown products from refined vegetable fats added to chocolate using method AOCS Ce 10/02 (02).",
      "categories": [
        "analysis sampling"
      ],
      "subcategories": [
        "analysis method heading",
        "analysis method"
      ],
      "page_range": {
        "start_page": 9,
        "end_page": 9
      }
    },
    {
      "section_id": 69,
      "order": 68,
      "section": "6.8.2 Quantitative Determination of Non-Cocoa Butter Vegetable Fats 2",
      "summary": "Describes quantitative determination of non‑cocoa butter vegetable fats by GC‑FID analysis of triacylglycerols (C50, C52, C54) per J. Amer. Oil Chem. Soc. (1980), noting that milk chocolate requires correction for milk fat.",
      "categories": [
        "analysis sampling"
      ],
      "subcategories": [
        "analysis method heading",
        "analysis method"
      ],
      "page_range": {
        "start_page": 9,
        "end_page": 9
      }
    }
  ]
}
